prefect_duckdb/__init__.py
prefect_duckdb/_version.py
prefect_duckdb/database.py
prefect_duckdb-0.1.0a1.dist-info/LICENSE
prefect_duckdb-0.1.0a1.dist-info/METADATA
prefect_duckdb-0.1.0a1.dist-info/WHEEL
prefect_duckdb-0.1.0a1.dist-info/entry_points.txt
prefect_duckdb-0.1.0a1.dist-info/top_level.txt
prefect_duckdb-0.1.0a1.dist-info/RECORD
